{"book_name":"Joel","chapter":2,"verses":[{"verse":1,"tokens":[{"t":"Blow","s":["H8628"]},{"t":"the"},{"t":"trumpet","s":["H7782"]},{"t":"in"},{"t":"Zion;","s":["H6726"]},{"t":"sound","s":["H7321"]},{"t":"the"},{"t":"alarm","s":["H7321"]},{"t":"on my"},{"t":"holy","s":["H6944"]},{"t":"hill.","s":["H2022"]},{"t":"Let all who live in the"},{"t":"land","s":["H776"]},{"t":"tremble,","s":["H7264"]},{"t":"for the"},{"t":"day","s":["H3117"]},{"t":"of the"},{"t":"Lord","s":["H3068"]},{"t":"is"},{"t":"coming.","s":["H935"]},{"t":"It is close at hand—"}]},{"verse":2,"tokens":[{"t":"a"},{"t":"day","s":["H3117"]},{"t":"of"},{"t":"darkness","s":["H2822"]},{"t":"and gloom, a"},{"t":"day","s":["H3117"]},{"t":"of"},{"t":"clouds","s":["H6051"]},{"t":"and blackness."},{"t":"Like","s":["H3254"]},{"t":"dawn"},{"t":"spreading","s":["H6566"]},{"t":"across the"},{"t":"mountains","s":["H2022"]},{"t":"a large and"},{"t":"mighty","s":["H7227"]},{"t":"army comes, such as never was in ancient times nor"},{"t":"ever","s":["H5769"]},{"t":"will be in"},{"t":"ages","s":["H8141"]},{"t":"to"},{"t":"come.","s":["H3254"]}]},{"verse":3,"tokens":[{"t":"Before","s":["H6440"]},{"t":"them"},{"t":"fire","s":["H784"]},{"t":"devours,","s":["H398"]},{"t":"behind","s":["H310"]},{"t":"them a"},{"t":"flame","s":["H3852"]},{"t":"blazes."},{"t":"Before","s":["H6440"]},{"t":"them the"},{"t":"land","s":["H776"]},{"t":"is like the"},{"t":"garden","s":["H1588"]},{"t":"of"},{"t":"Eden,","s":["H5731"]},{"t":"behind","s":["H310"]},{"t":"them, a"},{"t":"desert","s":["H4057"]},{"t":"waste—","s":["H8077"]},{"t":"nothing escapes them."}]},{"verse":4,"tokens":[{"t":"They have the"},{"t":"appearance","s":["H4758"]},{"t":"of"},{"t":"horses;","s":["H5483"]},{"t":"they gallop along like cavalry."}]},{"verse":5,"tokens":[{"t":"With a"},{"t":"noise","s":["H6963"]},{"t":"like","s":["H6963"]},{"t":"that of"},{"t":"chariots","s":["H4818"]},{"t":"they"},{"t":"leap","s":["H7540"]},{"t":"over the"},{"t":"mountaintops,","s":["H2022"]},{"t":"like","s":["H6963"]},{"t":"a"},{"t":"crackling","s":["H6963"]},{"t":"fire","s":["H784"]},{"t":"consuming"},{"t":"stubble,","s":["H7179"]},{"t":"like a"},{"t":"mighty","s":["H6099"]},{"t":"army drawn up for"},{"t":"battle.","s":["H4421"]}]},{"verse":6,"tokens":[{"t":"At the"},{"t":"sight","s":["H6440"]},{"t":"of them,"},{"t":"nations","s":["H5971"]},{"t":"are in anguish; every"},{"t":"face","s":["H6440"]},{"t":"turns pale."}]},{"verse":7,"tokens":[{"t":"They charge"},{"t":"like","s":["H1368"]},{"t":"warriors; they"},{"t":"scale","s":["H5927"]},{"t":"walls","s":["H2346"]},{"t":"like","s":["H582"]},{"t":"soldiers. They all"},{"t":"march","s":["H3212"]},{"t":"in line, not swerving from their course."}]},{"verse":8,"tokens":[{"t":"They do not jostle each other; each marches straight ahead. They plunge through defenses without breaking ranks."}]},{"verse":9,"tokens":[{"t":"They rush upon the"},{"t":"city;","s":["H5892"]},{"t":"they"},{"t":"run","s":["H7323"]},{"t":"along the"},{"t":"wall.","s":["H2346"]},{"t":"They"},{"t":"climb","s":["H5927"]},{"t":"into the"},{"t":"houses;","s":["H1004"]},{"t":"like thieves they"},{"t":"enter","s":["H935"]},{"t":"through the"},{"t":"windows.","s":["H2474"]}]},{"verse":10,"tokens":[{"t":"Before","s":["H6440"]},{"t":"them the"},{"t":"earth","s":["H776"]},{"t":"shakes, the"},{"t":"heavens","s":["H8064"]},{"t":"tremble,","s":["H7493"]},{"t":"the"},{"t":"sun","s":["H8121"]},{"t":"and"},{"t":"moon","s":["H3394"]},{"t":"are"},{"t":"darkened,","s":["H6937"]},{"t":"and the"},{"t":"stars","s":["H3556"]},{"t":"no longer shine."}]},{"verse":11,"tokens":[{"t":"The"},{"t":"Lord","s":["H3068"]},{"t":"thunders","s":["H6963"]},{"t":"at the head of his"},{"t":"army;","s":["H2428"]},{"t":"his forces are beyond number, and"},{"t":"mighty","s":["H7227"]},{"t":"is the"},{"t":"army","s":["H4264"]},{"t":"that obeys his command. The"},{"t":"day","s":["H3117"]},{"t":"of the"},{"t":"Lord","s":["H3068"]},{"t":"is"},{"t":"great;","s":["H1419"]},{"t":"it is"},{"t":"dreadful.","s":["H3372"]},{"t":"Who can"},{"t":"endure","s":["H6440"]},{"t":"it?"}]},{"verse":12,"tokens":[{"t":"“Even now,” declares the"},{"t":"Lord,","s":["H3068"]},{"t":"“return","s":["H7725"]},{"t":"to me with all your"},{"t":"heart,","s":["H3824"]},{"t":"with"},{"t":"fasting","s":["H6685"]},{"t":"and"},{"t":"weeping","s":["H1065"]},{"t":"and mourning.”"}]},{"verse":13,"tokens":[{"t":"Rend","s":["H7167"]},{"t":"your"},{"t":"heart","s":["H3824"]},{"t":"and not your"},{"t":"garments.","s":["H899"]},{"t":"Return","s":["H7725"]},{"t":"to the"},{"t":"Lord","s":["H3068"]},{"t":"your"},{"t":"God,","s":["H430"]},{"t":"for he is"},{"t":"gracious","s":["H2587"]},{"t":"and compassionate,"},{"t":"slow","s":["H750"]},{"t":"to"},{"t":"anger","s":["H639"]},{"t":"and"},{"t":"abounding","s":["H7227"]},{"t":"in love, and he relents from sending calamity."}]},{"verse":14,"tokens":[{"t":"Who"},{"t":"knows?","s":["H3045"]},{"t":"He may"},{"t":"turn","s":["H7725"]},{"t":"and relent and"},{"t":"leave","s":["H7604"]},{"t":"behind","s":["H310"]},{"t":"a"},{"t":"blessing—","s":["H1293"]},{"t":"grain"},{"t":"offerings","s":["H4503"]},{"t":"and"},{"t":"drink","s":["H5262"]},{"t":"offerings","s":["H5262"]},{"t":"for the"},{"t":"Lord","s":["H3068"]},{"t":"your God."}]},{"verse":15,"tokens":[{"t":"Blow","s":["H8628"]},{"t":"the"},{"t":"trumpet","s":["H7782"]},{"t":"in"},{"t":"Zion,","s":["H6726"]},{"t":"declare a"},{"t":"holy","s":["H6942"]},{"t":"fast,","s":["H6685"]},{"t":"call","s":["H7121"]},{"t":"a sacred assembly."}]},{"verse":16,"tokens":[{"t":"Gather","s":["H622"]},{"t":"the"},{"t":"people,","s":["H5971"]},{"t":"consecrate","s":["H6942"]},{"t":"the"},{"t":"assembly;","s":["H6951"]},{"t":"bring","s":["H6908"]},{"t":"together the"},{"t":"elders,","s":["H2205"]},{"t":"gather","s":["H622"]},{"t":"the"},{"t":"children,","s":["H5768"]},{"t":"those nursing at the"},{"t":"breast.","s":["H7699"]},{"t":"Let the"},{"t":"bridegroom","s":["H2860"]},{"t":"leave his room and the"},{"t":"bride","s":["H3618"]},{"t":"her"},{"t":"chamber.","s":["H2315"]}]},{"verse":17,"tokens":[{"t":"Let the"},{"t":"priests,","s":["H3548"]},{"t":"who"},{"t":"minister","s":["H8334"]},{"t":"before the"},{"t":"Lord,","s":["H3068"]},{"t":"weep","s":["H1058"]},{"t":"between","s":["H197"]},{"t":"the portico and the"},{"t":"altar.","s":["H4196"]},{"t":"Let them"},{"t":"say,","s":["H559"]},{"t":"“Spare","s":["H2347"]},{"t":"your"},{"t":"people,","s":["H5971"]},{"t":"Lord.","s":["H3068"]},{"t":"Do not"},{"t":"make","s":["H5414"]},{"t":"your"},{"t":"inheritance","s":["H5159"]},{"t":"an object of scorn, a byword among the"},{"t":"nations.","s":["H1471"]},{"t":"Why should they"},{"t":"say","s":["H559"]},{"t":"among","s":["H5971"]},{"t":"the"},{"t":"peoples,","s":["H5971"]},{"t":"‘Where is their God?’”"}]},{"verse":18,"tokens":[{"t":"Then the"},{"t":"Lord","s":["H3068"]},{"t":"was"},{"t":"jealous","s":["H7065"]},{"t":"for his"},{"t":"land","s":["H776"]},{"t":"and took"},{"t":"pity","s":["H2550"]},{"t":"on his people."}]},{"verse":19,"tokens":[{"t":"The"},{"t":"Lord","s":["H3068"]},{"t":"replied to them: “I am"},{"t":"sending","s":["H7971"]},{"t":"you grain, new"},{"t":"wine","s":["H8492"]},{"t":"and olive"},{"t":"oil,","s":["H3323"]},{"t":"enough to"},{"t":"satisfy","s":["H7646"]},{"t":"you"},{"t":"fully;","s":["H2781"]},{"t":"never again will I"},{"t":"make","s":["H5414"]},{"t":"you an object of scorn to the"},{"t":"nations.","s":["H5971"]}]},{"verse":20,"tokens":[{"t":"“I will"},{"t":"drive","s":["H5080"]},{"t":"the"},{"t":"northern","s":["H6830"]},{"t":"horde"},{"t":"far","s":["H7368"]},{"t":"from you, pushing it into a parched and"},{"t":"barren","s":["H6723"]},{"t":"land;","s":["H776"]},{"t":"its eastern ranks will drown in the Dead"},{"t":"Sea","s":["H3220"]},{"t":"and its western ranks in the Mediterranean"},{"t":"Sea.","s":["H3220"]},{"t":"And its stench will go up; its smell will"},{"t":"rise.”","s":["H5927"]},{"t":"Surely he has"},{"t":"done","s":["H6213"]},{"t":"great"},{"t":"things!","s":["H6931"]}]},{"verse":21,"tokens":[{"t":"Do not be"},{"t":"afraid,","s":["H3372"]},{"t":"land","s":["H127"]},{"t":"of Judah; be"},{"t":"glad","s":["H1523"]},{"t":"and"},{"t":"rejoice.","s":["H8055"]},{"t":"Surely the"},{"t":"Lord","s":["H3068"]},{"t":"has done great things!"}]},{"verse":22,"tokens":[{"t":"Do not be"},{"t":"afraid,","s":["H3372"]},{"t":"you"},{"t":"wild","s":["H7704"]},{"t":"animals, for the"},{"t":"pastures","s":["H4999"]},{"t":"in the"},{"t":"wilderness","s":["H4057"]},{"t":"are becoming green. The trees are"},{"t":"bearing","s":["H5375"]},{"t":"their"},{"t":"fruit;","s":["H6529"]},{"t":"the"},{"t":"fig","s":["H8384"]},{"t":"tree","s":["H8384"]},{"t":"and the"},{"t":"vine","s":["H1612"]},{"t":"yield","s":["H5414"]},{"t":"their riches."}]},{"verse":23,"tokens":[{"t":"Be"},{"t":"glad,","s":["H1523"]},{"t":"people","s":["H1121"]},{"t":"of"},{"t":"Zion,","s":["H6726"]},{"t":"rejoice","s":["H8055"]},{"t":"in the"},{"t":"Lord","s":["H3068"]},{"t":"your"},{"t":"God,","s":["H430"]},{"t":"for he has"},{"t":"given","s":["H5414"]},{"t":"you the autumn"},{"t":"rains","s":["H4175"]},{"t":"because he is faithful. He sends you abundant"},{"t":"showers,","s":["H1653"]},{"t":"both autumn and spring"},{"t":"rains,","s":["H4456"]},{"t":"as before."}]},{"verse":24,"tokens":[{"t":"The threshing"},{"t":"floors","s":["H1637"]},{"t":"will be filled with grain; the vats will"},{"t":"overflow","s":["H7783"]},{"t":"with new"},{"t":"wine","s":["H8492"]},{"t":"and oil."}]},{"verse":25,"tokens":[{"t":"“I will"},{"t":"repay","s":["H7999"]},{"t":"you for the"},{"t":"years","s":["H8141"]},{"t":"the"},{"t":"locusts","s":["H697"]},{"t":"have"},{"t":"eaten—","s":["H398"]},{"t":"the"},{"t":"great","s":["H1419"]},{"t":"locust and the young locust, the other locusts and the locust swarm— my great"},{"t":"army","s":["H2428"]},{"t":"that I sent among you."}]},{"verse":26,"tokens":[{"t":"You will have"},{"t":"plenty","s":["H398"]},{"t":"to"},{"t":"eat,","s":["H398"]},{"t":"until you are"},{"t":"full,","s":["H7646"]},{"t":"and you will"},{"t":"praise","s":["H1984"]},{"t":"the"},{"t":"name","s":["H8034"]},{"t":"of the"},{"t":"Lord","s":["H3068"]},{"t":"your"},{"t":"God,","s":["H430"]},{"t":"who has"},{"t":"worked","s":["H6213"]},{"t":"wonders","s":["H6381"]},{"t":"for you;"},{"t":"never","s":["H5769"]},{"t":"again will my"},{"t":"people","s":["H5971"]},{"t":"be shamed."}]},{"verse":27,"tokens":[{"t":"Then you will"},{"t":"know","s":["H3045"]},{"t":"that I am in"},{"t":"Israel,","s":["H3478"]},{"t":"that I am the"},{"t":"Lord","s":["H3068"]},{"t":"your"},{"t":"God,","s":["H430"]},{"t":"and that there is no other;"},{"t":"never","s":["H5769"]},{"t":"again will my"},{"t":"people","s":["H5971"]},{"t":"be shamed."}]},{"verse":28,"tokens":[{"t":"“And"},{"t":"afterward,","s":["H310"]},{"t":"I will"},{"t":"pour","s":["H8210"]},{"t":"out my"},{"t":"Spirit","s":["H7307"]},{"t":"on all people. Your"},{"t":"sons","s":["H1121"]},{"t":"and"},{"t":"daughters","s":["H1323"]},{"t":"will"},{"t":"prophesy,","s":["H5012"]},{"t":"your"},{"t":"old","s":["H2205"]},{"t":"men","s":["H2205"]},{"t":"will"},{"t":"dream","s":["H2492"]},{"t":"dreams,","s":["H2472"]},{"t":"your"},{"t":"young","s":["H970"]},{"t":"men","s":["H970"]},{"t":"will"},{"t":"see","s":["H7200"]},{"t":"visions."}]},{"verse":29,"tokens":[{"t":"Even on my"},{"t":"servants,","s":["H5650"]},{"t":"both men and women, I will"},{"t":"pour","s":["H8210"]},{"t":"out my Spirit in those"},{"t":"days.","s":["H3117"]}]},{"verse":30,"tokens":[{"t":"I will show"},{"t":"wonders","s":["H4159"]},{"t":"in the"},{"t":"heavens","s":["H8064"]},{"t":"and on the"},{"t":"earth,","s":["H776"]},{"t":"blood","s":["H1818"]},{"t":"and"},{"t":"fire","s":["H784"]},{"t":"and billows of smoke."}]},{"verse":31,"tokens":[{"t":"The"},{"t":"sun","s":["H8121"]},{"t":"will be"},{"t":"turned","s":["H2015"]},{"t":"to"},{"t":"darkness","s":["H2822"]},{"t":"and the"},{"t":"moon","s":["H3394"]},{"t":"to"},{"t":"blood","s":["H1818"]},{"t":"before","s":["H6440"]},{"t":"the coming of the"},{"t":"great","s":["H1419"]},{"t":"and"},{"t":"dreadful","s":["H3372"]},{"t":"day","s":["H3117"]},{"t":"of the"},{"t":"Lord.","s":["H3068"]}]},{"verse":32,"tokens":[{"t":"And everyone who calls on the"},{"t":"name","s":["H8034"]},{"t":"of the"},{"t":"Lord","s":["H3068"]},{"t":"will be saved; for on"},{"t":"Mount","s":["H2022"]},{"t":"Zion","s":["H6726"]},{"t":"and in"},{"t":"Jerusalem","s":["H3389"]},{"t":"there will be"},{"t":"deliverance,","s":["H6413"]},{"t":"as the"},{"t":"Lord","s":["H3068"]},{"t":"has"},{"t":"said,","s":["H559"]},{"t":"even among the survivors whom the"},{"t":"Lord","s":["H3068"]},{"t":"calls."}]}]}