{"book_name":"Genesis","chapter":48,"verses":[{"verse":1,"tokens":[{"t":"And it came to pass after","s":["H310"]},{"t":"these things,","s":["H1697"]},{"t":"that"},{"t":"one","i":1},{"t":"told","s":["H559"]},{"t":"Joseph,","s":["H3130"]},{"t":"Behold, thy father","s":["H1"]},{"t":"is","i":1},{"t":"sick:","s":["H2470"]},{"t":"and he took","s":["H3947"]},{"t":"with him his two","s":["H8147"]},{"t":"sons,","s":["H1121"]},{"t":"Manasseh","s":["H4519"]},{"t":"and Ephraim."}]},{"verse":2,"tokens":[{"t":"And"},{"t":"one","i":1},{"t":"told","s":["H5046"]},{"t":"Jacob,","s":["H3290"]},{"t":"and said,","s":["H559"]},{"t":"Behold, thy son","s":["H1121"]},{"t":"Joseph","s":["H3130"]},{"t":"cometh","s":["H935"]},{"t":"unto thee: and Israel","s":["H3478"]},{"t":"strengthened","s":["H2388"]},{"t":"himself, and sat","s":["H3427"]},{"t":"upon the bed."}]},{"verse":3,"tokens":[{"t":"And Jacob","s":["H3290"]},{"t":"said","s":["H559"]},{"t":"unto Joseph,","s":["H3130"]},{"t":"God","s":["H410"]},{"t":"Almighty","s":["H7706"]},{"t":"appeared","s":["H7200"]},{"t":"unto me at Luz","s":["H3870"]},{"t":"in the land","s":["H776"]},{"t":"of Canaan,","s":["H3667"]},{"t":"and blessed"},{"t":"me,"}]},{"verse":4,"tokens":[{"t":"And said","s":["H559"]},{"t":"unto me, Behold, I will make thee fruitful,","s":["H6509"]},{"t":"and multiply","s":["H7235"]},{"t":"thee, and I will make","s":["H5414"]},{"t":"of thee a multitude","s":["H6951"]},{"t":"of people;","s":["H5971"]},{"t":"and will give","s":["H5414"]},{"t":"this land","s":["H776"]},{"t":"to thy seed","s":["H2233"]},{"t":"after thee","s":["H310"]},{"t":"for","i":1},{"t":"an everlasting","s":["H5769"]},{"t":"possession."}]},{"verse":5,"tokens":[{"t":"And now thy two","s":["H8147"]},{"t":"sons,","s":["H1121"]},{"t":"Ephraim","s":["H669"]},{"t":"and Manasseh,","s":["H4519"]},{"t":"which were born","s":["H3205"]},{"t":"unto thee in the land","s":["H776"]},{"t":"of Egypt","s":["H4714"]},{"t":"before","s":["H5704"]},{"t":"I came","s":["H935"]},{"t":"unto thee into Egypt,","s":["H4714"]},{"t":"are","i":1},{"t":"mine; as Reuben","s":["H7205"]},{"t":"and Simeon,"},{"t":"they shall be mine."}]},{"verse":6,"tokens":[{"t":"And thy issue,","s":["H4138"]},{"t":"which thou begettest","s":["H3205"]},{"t":"after","s":["H310"]},{"t":"them, shall be thine,"},{"t":"and","i":1},{"t":"shall be called","s":["H7121"]},{"t":"after","s":["H5921"]},{"t":"the name","s":["H8034"]},{"t":"of their brethren","s":["H251"]},{"t":"in their inheritance."}]},{"verse":7,"tokens":[{"t":"And as for me, when I came","s":["H935"]},{"t":"from Padan,","s":["H6307"]},{"t":"Rachel","s":["H7354"]},{"t":"died","s":["H4191"]},{"t":"by me in the land","s":["H776"]},{"t":"of Canaan","s":["H3667"]},{"t":"in the way,","s":["H1870"]},{"t":"when","s":["H5750"]},{"t":"yet"},{"t":"there was","i":1},{"t":"but a little","s":["H3530"]},{"t":"way","s":["H776"]},{"t":"to come","s":["H935"]},{"t":"unto Ephrath:","s":["H672"]},{"t":"and I buried her","s":["H6912"]},{"t":"there in the way","s":["H1870"]},{"t":"of Ephrath;","s":["H672"]},{"t":"the same"},{"t":"is","i":1},{"t":"Bethlehem."}]},{"verse":8,"tokens":[{"t":"And Israel","s":["H3478"]},{"t":"beheld","s":["H7200"]},{"t":"Joseph's","s":["H3130"]},{"t":"sons,","s":["H1121"]},{"t":"and said,"},{"t":"Who are these?"}]},{"verse":9,"tokens":[{"t":"And Joseph","s":["H3130"]},{"t":"said","s":["H559"]},{"t":"unto his father,","s":["H1"]},{"t":"They"},{"t":"are","i":1},{"t":"my sons,","s":["H1121"]},{"t":"whom God","s":["H430"]},{"t":"hath given","s":["H5414"]},{"t":"me in this"},{"t":"place","i":1},{"t":". And he said,","s":["H559"]},{"t":"Bring them,","s":["H3947"]},{"t":"I pray thee, unto me, and I will bless"},{"t":"them."}]},{"verse":10,"tokens":[{"t":"Now the eyes","s":["H5869"]},{"t":"of Israel","s":["H3478"]},{"t":"were dim","s":["H3513"]},{"t":"for age,","s":["H2207"]},{"t":"so that","i":1},{"t":"he could","s":["H3201"]},{"t":"not see.","s":["H7200"]},{"t":"And he brought them near","s":["H5066"]},{"t":"unto him; and he kissed","s":["H5401"]},{"t":"them, and embraced"},{"t":"them."}]},{"verse":11,"tokens":[{"t":"And Israel","s":["H3478"]},{"t":"said","s":["H559"]},{"t":"unto Joseph,","s":["H3130"]},{"t":"I had not thought","s":["H6419"]},{"t":"to see","s":["H7200"]},{"t":"thy face:","s":["H6440"]},{"t":"and, lo, God","s":["H430"]},{"t":"hath shewed","s":["H7200"]},{"t":"me also thy seed."}]},{"verse":12,"tokens":[{"t":"And Joseph","s":["H3130"]},{"t":"brought them out","s":["H3318"]},{"t":"from between","s":["H5973"]},{"t":"his knees,","s":["H1290"]},{"t":"and he bowed","s":["H7812"]},{"t":"himself with his face","s":["H639"]},{"t":"to the earth."}]},{"verse":13,"tokens":[{"t":"And Joseph","s":["H3130"]},{"t":"took","s":["H3947"]},{"t":"them both,","s":["H8147"]},{"t":"Ephraim","s":["H669"]},{"t":"in his right hand","s":["H3225"]},{"t":"toward Israel's","s":["H3478"]},{"t":"left hand,","s":["H8040"]},{"t":"and Manasseh","s":["H4519"]},{"t":"in his left hand","s":["H8040"]},{"t":"toward Israel's","s":["H3478"]},{"t":"right hand,","s":["H3225"]},{"t":"and brought"},{"t":"them","i":1},{"t":"near"},{"t":"unto him."}]},{"verse":14,"tokens":[{"t":"And Israel","s":["H3478"]},{"t":"stretched out","s":["H7971"]},{"t":"his right hand,","s":["H3225"]},{"t":"and laid","s":["H7896"]},{"t":"it","i":1},{"t":"upon Ephraim's","s":["H669"]},{"t":"head,","s":["H7218"]},{"t":"who"},{"t":"was","i":1},{"t":"the younger,","s":["H6810"]},{"t":"and his left hand","s":["H8040"]},{"t":"upon Manasseh's","s":["H4519"]},{"t":"head,","s":["H7218"]},{"t":"guiding","s":["H7919"]},{"t":"his hands","s":["H3027"]},{"t":"wittingly;","s":["H7919"]},{"t":"for Manasseh","s":["H4519"]},{"t":"was","i":1},{"t":"the firstborn."}]},{"verse":15,"tokens":[{"t":"And he blessed","s":["H1288"]},{"t":"Joseph,","s":["H3130"]},{"t":"and said,","s":["H559"]},{"t":"God,","s":["H430"]},{"t":"before","s":["H6440"]},{"t":"whom my fathers","s":["H1"]},{"t":"Abraham","s":["H85"]},{"t":"and Isaac","s":["H3327"]},{"t":"did walk,","s":["H1980"]},{"t":"the God","s":["H430"]},{"t":"which fed","s":["H7462"]},{"t":"me all my life long","s":["H5750"]},{"t":"unto this day,"}]},{"verse":16,"tokens":[{"t":"The Angel","s":["H4397"]},{"t":"which redeemed","s":["H1350"]},{"t":"me from all evil,","s":["H7451"]},{"t":"bless","s":["H1288"]},{"t":"the lads;","s":["H5288"]},{"t":"and let my name","s":["H8034"]},{"t":"be named","s":["H7121"]},{"t":"on them, and the name","s":["H8034"]},{"t":"of my fathers","s":["H1"]},{"t":"Abraham","s":["H85"]},{"t":"and Isaac;","s":["H3327"]},{"t":"and let them grow","s":["H1711"]},{"t":"into a multitude","s":["H7230"]},{"t":"in the midst","s":["H7130"]},{"t":"of the earth."}]},{"verse":17,"tokens":[{"t":"And when Joseph","s":["H3130"]},{"t":"saw","s":["H7200"]},{"t":"that his father","s":["H1"]},{"t":"laid","s":["H7896"]},{"t":"his right","s":["H3225"]},{"t":"hand","s":["H3027"]},{"t":"upon the head","s":["H7218"]},{"t":"of Ephraim,","s":["H669"]},{"t":"it displeased","s":["H3415","H5869"]},{"t":"him: and he held up","s":["H8551"]},{"t":"his father's","s":["H1"]},{"t":"hand,","s":["H3027"]},{"t":"to remove","s":["H5493"]},{"t":"it from Ephraim's","s":["H669"]},{"t":"head","s":["H7218"]},{"t":"unto Manasseh's","s":["H4519"]},{"t":"head."}]},{"verse":18,"tokens":[{"t":"And Joseph","s":["H3130"]},{"t":"said","s":["H559"]},{"t":"unto his father,","s":["H1"]},{"t":"Not so, my father:","s":["H1"]},{"t":"for this"},{"t":"is","i":1},{"t":"the firstborn;","s":["H1060"]},{"t":"put","s":["H7760"]},{"t":"thy right hand","s":["H3225"]},{"t":"upon his head."}]},{"verse":19,"tokens":[{"t":"And his father","s":["H1"]},{"t":"refused,","s":["H3985"]},{"t":"and said,","s":["H559"]},{"t":"I know","s":["H3045"]},{"t":"it","i":1},{"t":", my son,","s":["H1121"]},{"t":"I know","s":["H3045"]},{"t":"it","i":1},{"t":": he also shall become a people,","s":["H5971"]},{"t":"and he also shall be great:","s":["H1431"]},{"t":"but truly","s":["H199"]},{"t":"his younger","s":["H6996"]},{"t":"brother","s":["H251"]},{"t":"shall be greater","s":["H1431"]},{"t":"than he, and his seed","s":["H2233"]},{"t":"shall become a multitude","s":["H4393"]},{"t":"of nations."}]},{"verse":20,"tokens":[{"t":"And he blessed","s":["H1288"]},{"t":"them that day,","s":["H3117"]},{"t":"saying,","s":["H559"]},{"t":"In thee shall Israel","s":["H3478"]},{"t":"bless,","s":["H1288"]},{"t":"saying,","s":["H559"]},{"t":"God","s":["H430"]},{"t":"make","s":["H7760"]},{"t":"thee as Ephraim","s":["H669"]},{"t":"and as Manasseh:","s":["H4519"]},{"t":"and he set","s":["H7760"]},{"t":"Ephraim","s":["H669"]},{"t":"before","s":["H6440"]},{"t":"Manasseh."}]},{"verse":21,"tokens":[{"t":"And Israel","s":["H3478"]},{"t":"said","s":["H559"]},{"t":"unto Joseph,","s":["H3130"]},{"t":"Behold, I die:","s":["H4191"]},{"t":"but God","s":["H430"]},{"t":"shall be with you, and bring you again","s":["H7725"]},{"t":"unto the land","s":["H776"]},{"t":"of your fathers."}]},{"verse":22,"tokens":[{"t":"Moreover I have given","s":["H5414"]},{"t":"to thee one","s":["H259"]},{"t":"portion","s":["H7926"]},{"t":"above thy brethren,","s":["H251"]},{"t":"which I took","s":["H3947"]},{"t":"out of the hand","s":["H3027"]},{"t":"of the Amorite","s":["H567"]},{"t":"with my sword","s":["H2719"]},{"t":"and with my bow."}]}]}