{"book_name":"Psalms","chapter":44,"verses":[{"verse":1,"tokens":[{"t":"O"},{"t":"God,","s":["H430"]},{"t":"we have"},{"t":"heard","s":["H8085"]},{"t":"with our"},{"t":"ears,","s":["H241"]},{"t":"our"},{"t":"fathers","s":["H1"]},{"t":"have"},{"t":"told","s":["H5608"]},{"t":"us, what"},{"t":"deeds","s":["H6467"]},{"t":"you performed in their"},{"t":"days,","s":["H3117"]},{"t":"in the"},{"t":"days","s":["H3117"]},{"t":"of"},{"t":"old:","s":["H1121"]}]},{"verse":2,"tokens":[{"t":"you with your own"},{"t":"hand","s":["H3027"]},{"t":"drove out the"},{"t":"nations,","s":["H1471"]},{"t":"but them you"},{"t":"planted;","s":["H5193"]},{"t":"you"},{"t":"afflicted","s":["H7489"]},{"t":"the"},{"t":"peoples,","s":["H3816"]},{"t":"but them you set free;"}]},{"verse":3,"tokens":[{"t":"for not by their own"},{"t":"sword","s":["H2719"]},{"t":"did they win the"},{"t":"land,","s":["H776"]},{"t":"nor did their own"},{"t":"arm","s":["H2220"]},{"t":"save","s":["H3467"]},{"t":"them, but your"},{"t":"right","s":["H3225"]},{"t":"hand","s":["H3225"]},{"t":"and your"},{"t":"arm,","s":["H2220"]},{"t":"and the"},{"t":"light","s":["H216"]},{"t":"of your"},{"t":"face,","s":["H6440"]},{"t":"for you delighted in them."}]},{"verse":4,"tokens":[{"t":"You are my"},{"t":"King,","s":["H4428"]},{"t":"O"},{"t":"God;","s":["H430"]},{"t":"ordain"},{"t":"salvation","s":["H3444"]},{"t":"for Jacob!"}]},{"verse":5,"tokens":[{"t":"Through","s":["H5055"]},{"t":"you we"},{"t":"push","s":["H5055"]},{"t":"down","s":["H5055"]},{"t":"our"},{"t":"foes;","s":["H6862"]},{"t":"through","s":["H8034"]},{"t":"your"},{"t":"name","s":["H8034"]},{"t":"we"},{"t":"tread","s":["H947"]},{"t":"down","s":["H947"]},{"t":"those who rise up against us."}]},{"verse":6,"tokens":[{"t":"For not in my"},{"t":"bow","s":["H7198"]},{"t":"do I"},{"t":"trust,","s":["H982"]},{"t":"nor can my"},{"t":"sword","s":["H2719"]},{"t":"save me."}]},{"verse":7,"tokens":[{"t":"But you have"},{"t":"saved","s":["H3467"]},{"t":"us from our"},{"t":"foes","s":["H6862"]},{"t":"and have"},{"t":"put","s":["H954"]},{"t":"to"},{"t":"shame","s":["H954"]},{"t":"those who hate us."}]},{"verse":8,"tokens":[{"t":"In"},{"t":"God","s":["H430"]},{"t":"we have"},{"t":"boasted","s":["H1984"]},{"t":"continually,","s":["H3117"]},{"t":"and we will"},{"t":"give","s":["H3034"]},{"t":"thanks to your"},{"t":"name","s":["H8034"]},{"t":"forever. Selah"}]},{"verse":9,"tokens":[{"t":"But you have rejected us and disgraced us and have not gone out with our armies."}]},{"verse":10,"tokens":[{"t":"You have made us"},{"t":"turn","s":["H7725"]},{"t":"back","s":["H268"]},{"t":"from the"},{"t":"foe,","s":["H6862"]},{"t":"and those who"},{"t":"hate","s":["H8130"]},{"t":"us have gotten spoil."}]},{"verse":11,"tokens":[{"t":"You have"},{"t":"made","s":["H5414"]},{"t":"us"},{"t":"like","s":["H6629"]},{"t":"sheep","s":["H6629"]},{"t":"for slaughter and have"},{"t":"scattered","s":["H2219"]},{"t":"us among the nations."}]},{"verse":12,"tokens":[{"t":"You have sold your people for a trifle, demanding no high price for them."}]},{"verse":13,"tokens":[{"t":"You have made us the taunt of our neighbors, the"},{"t":"derision","s":["H7047"]},{"t":"and"},{"t":"scorn","s":["H3933"]},{"t":"of those around us."}]},{"verse":14,"tokens":[{"t":"You have made us a"},{"t":"byword","s":["H4912"]},{"t":"among","s":["H1471"]},{"t":"the"},{"t":"nations,","s":["H1471"]},{"t":"a laughingstock among the peoples."}]},{"verse":15,"tokens":[{"t":"All"},{"t":"day","s":["H3117"]},{"t":"long my disgrace is"},{"t":"before","s":["H1322"]},{"t":"me, and"},{"t":"shame","s":["H1322"]},{"t":"has covered my"},{"t":"face","s":["H6440"]}]},{"verse":16,"tokens":[{"t":"at the"},{"t":"sound","s":["H6963"]},{"t":"of the taunter and reviler, at the"},{"t":"sight","s":["H6440"]},{"t":"of the"},{"t":"enemy","s":["H341"]},{"t":"and the avenger."}]},{"verse":17,"tokens":[{"t":"All this has"},{"t":"come","s":["H935"]},{"t":"upon us, though we have not"},{"t":"forgotten","s":["H7911"]},{"t":"you, and we have not been"},{"t":"false","s":["H8266"]},{"t":"to your covenant."}]},{"verse":18,"tokens":[{"t":"Our"},{"t":"heart","s":["H3820"]},{"t":"has not"},{"t":"turned","s":["H5472"]},{"t":"back,","s":["H268"]},{"t":"nor have our"},{"t":"steps","s":["H838"]},{"t":"departed from your way;"}]},{"verse":19,"tokens":[{"t":"yet you have"},{"t":"broken","s":["H1794"]},{"t":"us in the"},{"t":"place","s":["H4725"]},{"t":"of jackals and"},{"t":"covered","s":["H3680"]},{"t":"us with the shadow of death."}]},{"verse":20,"tokens":[{"t":"If we had"},{"t":"forgotten","s":["H7911"]},{"t":"the"},{"t":"name","s":["H8034"]},{"t":"of our"},{"t":"God","s":["H430"]},{"t":"or"},{"t":"spread","s":["H6566"]},{"t":"out our"},{"t":"hands","s":["H3709"]},{"t":"to a foreign god,"}]},{"verse":21,"tokens":[{"t":"would not"},{"t":"God","s":["H430"]},{"t":"discover this? For he"},{"t":"knows","s":["H3045"]},{"t":"the"},{"t":"secrets","s":["H8587"]},{"t":"of the heart."}]},{"verse":22,"tokens":[{"t":"Yet for your"},{"t":"sake","s":["H2026"]},{"t":"we are"},{"t":"killed","s":["H2026"]},{"t":"all the"},{"t":"day","s":["H3117"]},{"t":"long;","s":["H2803"]},{"t":"we are"},{"t":"regarded","s":["H2803"]},{"t":"as"},{"t":"sheep","s":["H6629"]},{"t":"to be slaughtered."}]},{"verse":23,"tokens":[{"t":"Awake!","s":["H5782"]},{"t":"Why are you"},{"t":"sleeping,","s":["H3462"]},{"t":"O"},{"t":"Lord?","s":["H136"]},{"t":"Rouse yourself! Do not reject us forever!"}]},{"verse":24,"tokens":[{"t":"Why do you"},{"t":"hide","s":["H5641"]},{"t":"your"},{"t":"face?","s":["H6440"]},{"t":"Why do you"},{"t":"forget","s":["H7911"]},{"t":"our"},{"t":"affliction","s":["H6040"]},{"t":"and oppression?"}]},{"verse":25,"tokens":[{"t":"For our"},{"t":"soul","s":["H5315"]},{"t":"is"},{"t":"bowed","s":["H7743"]},{"t":"down","s":["H7743"]},{"t":"to the"},{"t":"dust;","s":["H6083"]},{"t":"our"},{"t":"belly","s":["H990"]},{"t":"clings to the ground."}]},{"verse":26,"tokens":[{"t":"Rise","s":["H6965"]},{"t":"up; come to our"},{"t":"help!","s":["H5833"]},{"t":"Redeem","s":["H6299"]},{"t":"us for the sake of your steadfast love!"}]}]}