{"book_name":"Isaiah","chapter":63,"verses":[{"verse":1,"tokens":[{"t":"Who is this who"},{"t":"comes","s":["H935"]},{"t":"from"},{"t":"Edom,","s":["H123"]},{"t":"With"},{"t":"dyed","s":["H2556"]},{"t":"garments","s":["H899"]},{"t":"from"},{"t":"Bozrah,","s":["H1224"]},{"t":"This One who is"},{"t":"glorious","s":["H1921"]},{"t":"in His"},{"t":"apparel,","s":["H3830"]},{"t":"Traveling","s":["H6808"]},{"t":"in the"},{"t":"greatness","s":["H7230"]},{"t":"of His"},{"t":"strength?—","s":["H3581"]},{"t":"“I who"},{"t":"speak","s":["H1696"]},{"t":"in"},{"t":"righteousness,","s":["H6666"]},{"t":"mighty","s":["H7227"]},{"t":"to save.”"}]},{"verse":2,"tokens":[{"t":"Why is Your"},{"t":"apparel","s":["H3830"]},{"t":"red,","s":["H122"]},{"t":"And Your"},{"t":"garments","s":["H899"]},{"t":"like","s":["H1869"]},{"t":"one who"},{"t":"treads","s":["H1869"]},{"t":"in the winepress?"}]},{"verse":3,"tokens":[{"t":"“I have"},{"t":"trodden","s":["H1869"]},{"t":"the"},{"t":"winepress","s":["H6333"]},{"t":"alone,","s":["H5971"]},{"t":"And from the"},{"t":"peoples","s":["H5971"]},{"t":"no one was with Me. For I have trodden them in My"},{"t":"anger,","s":["H639"]},{"t":"And"},{"t":"trampled","s":["H7429"]},{"t":"them in My"},{"t":"fury;","s":["H2534"]},{"t":"Their"},{"t":"blood","s":["H5332"]},{"t":"is"},{"t":"sprinkled","s":["H5137"]},{"t":"upon My"},{"t":"garments,","s":["H899"]},{"t":"And I have"},{"t":"stained","s":["H1351"]},{"t":"all My robes."}]},{"verse":4,"tokens":[{"t":"For the"},{"t":"day","s":["H3117"]},{"t":"of"},{"t":"vengeance","s":["H5359"]},{"t":"is in My"},{"t":"heart,","s":["H3820"]},{"t":"And the"},{"t":"year","s":["H8141"]},{"t":"of My"},{"t":"redeemed","s":["H1350"]},{"t":"has come."}]},{"verse":5,"tokens":[{"t":"I"},{"t":"looked,","s":["H5027"]},{"t":"but there was no one to"},{"t":"help,","s":["H5826"]},{"t":"And I"},{"t":"wondered","s":["H8074"]},{"t":"That there was no one to"},{"t":"uphold;","s":["H5564"]},{"t":"Therefore My own"},{"t":"arm","s":["H2220"]},{"t":"brought","s":["H3467"]},{"t":"salvation","s":["H3467"]},{"t":"for Me; And My own"},{"t":"fury,","s":["H2534"]},{"t":"it"},{"t":"sustained","s":["H5564"]},{"t":"Me."}]},{"verse":6,"tokens":[{"t":"I have trodden"},{"t":"down","s":["H947"]},{"t":"the"},{"t":"peoples","s":["H5971"]},{"t":"in My"},{"t":"anger,","s":["H639"]},{"t":"Made them"},{"t":"drunk","s":["H7937"]},{"t":"in My"},{"t":"fury,","s":["H2534"]},{"t":"And brought"},{"t":"down","s":["H3381"]},{"t":"their"},{"t":"strength","s":["H5332"]},{"t":"to the earth.”"}]},{"verse":7,"tokens":[{"t":"I will"},{"t":"mention","s":["H2142"]},{"t":"the"},{"t":"lovingkindnesses","s":["H2617"]},{"t":"of the"},{"t":"Lord","s":["H3068"]},{"t":"And the"},{"t":"praises","s":["H8416"]},{"t":"of the"},{"t":"Lord,","s":["H3068"]},{"t":"According","s":["H3068"]},{"t":"to all that the"},{"t":"Lord","s":["H3068"]},{"t":"has"},{"t":"bestowed","s":["H1580"]},{"t":"on us, And the"},{"t":"great","s":["H7227"]},{"t":"goodness","s":["H2898"]},{"t":"toward","s":["H1004"]},{"t":"the"},{"t":"house","s":["H1004"]},{"t":"of"},{"t":"Israel,","s":["H3478"]},{"t":"Which He has"},{"t":"bestowed","s":["H1580"]},{"t":"on them"},{"t":"according","s":["H7356"]},{"t":"to His"},{"t":"mercies,","s":["H7356"]},{"t":"According","s":["H7230"]},{"t":"to the"},{"t":"multitude","s":["H7230"]},{"t":"of His lovingkindnesses."}]},{"verse":8,"tokens":[{"t":"For He"},{"t":"said,","s":["H559"]},{"t":"“Surely they are My"},{"t":"people,","s":["H5971"]},{"t":"Children","s":["H1121"]},{"t":"who will not"},{"t":"lie.”","s":["H8266"]},{"t":"So He became their Savior."}]},{"verse":9,"tokens":[{"t":"In all their"},{"t":"affliction","s":["H6869"]},{"t":"He was"},{"t":"afflicted,","s":["H6862"]},{"t":"And the"},{"t":"Angel","s":["H4397"]},{"t":"of His"},{"t":"Presence","s":["H6440"]},{"t":"saved","s":["H3467"]},{"t":"them; In His"},{"t":"love","s":["H160"]},{"t":"and in His"},{"t":"pity","s":["H2551"]},{"t":"He"},{"t":"redeemed","s":["H1350"]},{"t":"them; And He bore them and"},{"t":"carried","s":["H5375"]},{"t":"them All the"},{"t":"days","s":["H3117"]},{"t":"of old."}]},{"verse":10,"tokens":[{"t":"But they"},{"t":"rebelled","s":["H4784"]},{"t":"and grieved His"},{"t":"Holy","s":["H6944"]},{"t":"Spirit;","s":["H7307"]},{"t":"So He"},{"t":"turned","s":["H2015"]},{"t":"Himself against them as an"},{"t":"enemy,","s":["H341"]},{"t":"And He fought against them."}]},{"verse":11,"tokens":[{"t":"Then he"},{"t":"remembered","s":["H2142"]},{"t":"the"},{"t":"days","s":["H3117"]},{"t":"of"},{"t":"old,","s":["H5769"]},{"t":"Moses","s":["H4872"]},{"t":"and his"},{"t":"people,","s":["H5971"]},{"t":"saying: “Where is He who"},{"t":"brought","s":["H5927"]},{"t":"them up out of the"},{"t":"sea","s":["H3220"]},{"t":"With the"},{"t":"shepherd","s":["H7462"]},{"t":"of His"},{"t":"flock?","s":["H6629"]},{"t":"Where is He who"},{"t":"put","s":["H7760"]},{"t":"His"},{"t":"Holy","s":["H6944"]},{"t":"Spirit","s":["H7307"]},{"t":"within them,"}]},{"verse":12,"tokens":[{"t":"Who"},{"t":"led","s":["H3212"]},{"t":"them by the"},{"t":"right","s":["H3225"]},{"t":"hand","s":["H3225"]},{"t":"of"},{"t":"Moses,","s":["H4872"]},{"t":"With His"},{"t":"glorious","s":["H8597"]},{"t":"arm,","s":["H2220"]},{"t":"Dividing","s":["H1234"]},{"t":"the"},{"t":"water","s":["H4325"]},{"t":"before","s":["H6440"]},{"t":"them To"},{"t":"make","s":["H6213"]},{"t":"for"},{"t":"Himself","s":["H5769"]},{"t":"an"},{"t":"everlasting","s":["H5769"]},{"t":"name,"}]},{"verse":13,"tokens":[{"t":"Who"},{"t":"led","s":["H3212"]},{"t":"them"},{"t":"through","s":["H8415"]},{"t":"the"},{"t":"deep,","s":["H8415"]},{"t":"As a"},{"t":"horse","s":["H5483"]},{"t":"in the"},{"t":"wilderness,","s":["H4057"]},{"t":"That they might not stumble?”"}]},{"verse":14,"tokens":[{"t":"As a"},{"t":"beast","s":["H929"]},{"t":"goes"},{"t":"down","s":["H3381"]},{"t":"into the"},{"t":"valley,","s":["H1237"]},{"t":"And the"},{"t":"Spirit","s":["H7307"]},{"t":"of the"},{"t":"Lord","s":["H3068"]},{"t":"causes","s":["H5117"]},{"t":"him to"},{"t":"rest,","s":["H5117"]},{"t":"So You"},{"t":"lead","s":["H5090"]},{"t":"Your"},{"t":"people,","s":["H5971"]},{"t":"To"},{"t":"make","s":["H6213"]},{"t":"Yourself a"},{"t":"glorious","s":["H8597"]},{"t":"name."}]},{"verse":15,"tokens":[{"t":"Look","s":["H5027"]},{"t":"down","s":["H5027"]},{"t":"from"},{"t":"heaven,","s":["H8064"]},{"t":"And"},{"t":"see","s":["H7200"]},{"t":"from Your"},{"t":"habitation,","s":["H2073"]},{"t":"holy","s":["H6944"]},{"t":"and"},{"t":"glorious.","s":["H8597"]},{"t":"Where are Your"},{"t":"zeal","s":["H7068"]},{"t":"and Your"},{"t":"strength,","s":["H1369"]},{"t":"The yearning of Your"},{"t":"heart","s":["H4578"]},{"t":"and Your"},{"t":"mercies","s":["H7356"]},{"t":"toward me? Are they restrained?"}]},{"verse":16,"tokens":[{"t":"Doubtless","s":["H3588"]},{"t":"You are our"},{"t":"Father,","s":["H1"]},{"t":"Though","s":["H85"]},{"t":"Abraham","s":["H85"]},{"t":"was"},{"t":"ignorant","s":["H3808","H3045"]},{"t":"of us, And"},{"t":"Israel","s":["H3478"]},{"t":"does not"},{"t":"acknowledge","s":["H5234"]},{"t":"us. You, O"},{"t":"Lord,","s":["H3068"]},{"t":"are our"},{"t":"Father;","s":["H1"]},{"t":"Our"},{"t":"Redeemer","s":["H1350"]},{"t":"from Everlasting is Your"},{"t":"name.","s":["H8034"]}]},{"verse":17,"tokens":[{"t":"O"},{"t":"Lord,","s":["H3068"]},{"t":"why have You"},{"t":"made","s":["H8582"]},{"t":"us stray from Your"},{"t":"ways,","s":["H1870"]},{"t":"And"},{"t":"hardened","s":["H7188"]},{"t":"our"},{"t":"heart","s":["H3820"]},{"t":"from Your"},{"t":"fear?","s":["H3374"]},{"t":"Return","s":["H7725"]},{"t":"for Your"},{"t":"servants’","s":["H5650"]},{"t":"sake,","s":["H7626"]},{"t":"The"},{"t":"tribes","s":["H7626"]},{"t":"of Your inheritance."}]},{"verse":18,"tokens":[{"t":"Your"},{"t":"holy","s":["H6944"]},{"t":"people","s":["H5971"]},{"t":"have"},{"t":"possessed","s":["H3423"]},{"t":"it but a"},{"t":"little","s":["H4705"]},{"t":"while; Our"},{"t":"adversaries","s":["H6862"]},{"t":"have"},{"t":"trodden","s":["H947"]},{"t":"down","s":["H947"]},{"t":"Your sanctuary."}]},{"verse":19,"tokens":[{"t":"We have become like those of old,"},{"t":"over","s":["H7121"]},{"t":"whom You"},{"t":"never","s":["H5769"]},{"t":"ruled, Those who were never"},{"t":"called","s":["H7121"]},{"t":"by Your name."}]}]}