{"book_name":"Luke","chapter":21,"verses":[{"verse":1,"tokens":[{"t":"And having"},{"t":"looked","s":["G308"]},{"t":"up, he"},{"t":"saw","s":["G1492"]},{"t":"those who did"},{"t":"cast","s":["G906"]},{"t":"their"},{"t":"gifts","s":["G1435"]},{"t":"to the treasury --"},{"t":"rich","s":["G4145"]},{"t":"men,","s":["G4145"]}]},{"verse":2,"tokens":[{"t":"and he"},{"t":"saw","s":["G1492"]},{"t":"also a"},{"t":"certain","s":["G5100"]},{"t":"poor","s":["G3998"]},{"t":"widow","s":["G5503"]},{"t":"casting","s":["G906"]},{"t":"there"},{"t":"two","s":["G1417"]},{"t":"mites,"}]},{"verse":3,"tokens":[{"t":"and he"},{"t":"said,","s":["G2036"]},{"t":"`Truly","s":["G230"]},{"t":"I"},{"t":"say","s":["G3004"]},{"t":"to you, that this"},{"t":"poor","s":["G4434"]},{"t":"widow","s":["G5503"]},{"t":"did"},{"t":"cast","s":["G906"]},{"t":"in"},{"t":"more","s":["G4119"]},{"t":"than","s":["G4119"]},{"t":"all;"}]},{"verse":4,"tokens":[{"t":"for all these out of their superabundance did"},{"t":"cast","s":["G906"]},{"t":"into the"},{"t":"gifts","s":["G1435"]},{"t":"to"},{"t":"God,","s":["G2316"]},{"t":"but this one out of her"},{"t":"want,","s":["G5303"]},{"t":"all the"},{"t":"living","s":["G979"]},{"t":"that she had, did"},{"t":"cast","s":["G906"]},{"t":"in.'"}]},{"verse":5,"tokens":[{"t":"And"},{"t":"certain","s":["G5100"]},{"t":"saying","s":["G3004"]},{"t":"about the"},{"t":"temple,","s":["G2411"]},{"t":"that with"},{"t":"goodly","s":["G2570"]},{"t":"stones","s":["G3037"]},{"t":"and devoted things it hath been"},{"t":"adorned,","s":["G2885"]},{"t":"he said,"}]},{"verse":6,"tokens":[{"t":"`These"},{"t":"things","s":["G5023"]},{"t":"that ye"},{"t":"behold","s":["G2334"]},{"t":"--"},{"t":"days","s":["G2250"]},{"t":"will"},{"t":"come,","s":["G2064"]},{"t":"in which there shall not be"},{"t":"left","s":["G863"]},{"t":"a"},{"t":"stone","s":["G3037"]},{"t":"upon a"},{"t":"stone,","s":["G3037"]},{"t":"that shall not be thrown down.'"}]},{"verse":7,"tokens":[{"t":"And they"},{"t":"questioned","s":["G1905"]},{"t":"him,"},{"t":"saying,","s":["G3004"]},{"t":"`Teacher,","s":["G1320"]},{"t":"when, then, shall these"},{"t":"things","s":["G5023"]},{"t":"be? and what [is] the"},{"t":"sign","s":["G4592"]},{"t":"when these"},{"t":"things","s":["G5023"]},{"t":"may be about to happen?'"}]},{"verse":8,"tokens":[{"t":"And he"},{"t":"said,","s":["G2036"]},{"t":"`See","s":["G991"]},{"t":"-- ye may not be led"},{"t":"astray,","s":["G4105"]},{"t":"for"},{"t":"many","s":["G4183"]},{"t":"shall"},{"t":"come","s":["G2064"]},{"t":"in my"},{"t":"name,","s":["G3686"]},{"t":"saying","s":["G3004","G3754"]},{"t":"-- I am [he], and the"},{"t":"time","s":["G2540"]},{"t":"hath"},{"t":"come","s":["G1448"]},{"t":"nigh;"},{"t":"go","s":["G4198"]},{"t":"not on then"},{"t":"after","s":["G3694"]},{"t":"them;"}]},{"verse":9,"tokens":[{"t":"and when ye may"},{"t":"hear","s":["G191"]},{"t":"of"},{"t":"wars","s":["G4171"]},{"t":"and uprisings, be not"},{"t":"terrified,","s":["G4422"]},{"t":"for it behoveth these"},{"t":"things","s":["G5023"]},{"t":"to"},{"t":"happen","s":["G1096"]},{"t":"first,","s":["G4412"]},{"t":"but the"},{"t":"end","s":["G5056"]},{"t":"[is] not immediately.'"}]},{"verse":10,"tokens":[{"t":"Then"},{"t":"said","s":["G3004"]},{"t":"he to them,"},{"t":"`Nation","s":["G1484"]},{"t":"shall"},{"t":"rise","s":["G1453"]},{"t":"against","s":["G1909"]},{"t":"nation,","s":["G1484"]},{"t":"and"},{"t":"kingdom","s":["G932"]},{"t":"against","s":["G1909"]},{"t":"kingdom,"}]},{"verse":11,"tokens":[{"t":"great","s":["G3173"]},{"t":"shakings also in every"},{"t":"place,","s":["G5117"]},{"t":"and"},{"t":"famines,","s":["G3042"]},{"t":"and"},{"t":"pestilences,","s":["G3061"]},{"t":"there shall be;"},{"t":"fearful","s":["G5400"]},{"t":"things also, and"},{"t":"great","s":["G3173"]},{"t":"signs","s":["G4592"]},{"t":"from heaven there shall be;"}]},{"verse":12,"tokens":[{"t":"and"},{"t":"before","s":["G4253"]},{"t":"all these, they shall"},{"t":"lay","s":["G1911"]},{"t":"on you their"},{"t":"hands,","s":["G5495"]},{"t":"and"},{"t":"persecute,","s":["G1377"]},{"t":"delivering","s":["G3860"]},{"t":"up to"},{"t":"synagogues","s":["G4864"]},{"t":"and"},{"t":"prisons,","s":["G5438"]},{"t":"being"},{"t":"brought","s":["G71"]},{"t":"before","s":["G1909"]},{"t":"kings","s":["G935"]},{"t":"and"},{"t":"governors","s":["G2232"]},{"t":"for my"},{"t":"name's","s":["G3686"]},{"t":"sake;"}]},{"verse":13,"tokens":[{"t":"and it shall"},{"t":"become","s":["G576"]},{"t":"to you for a testimony."}]},{"verse":14,"tokens":[{"t":"`Settle,","s":["G5087"]},{"t":"then, to your"},{"t":"hearts,","s":["G2588"]},{"t":"not to"},{"t":"meditate","s":["G4304"]},{"t":"beforehand to reply,"}]},{"verse":15,"tokens":[{"t":"for I will"},{"t":"give","s":["G1325"]},{"t":"to you a"},{"t":"mouth","s":["G4750"]},{"t":"and"},{"t":"wisdom","s":["G4678"]},{"t":"that all your opposers shall not be"},{"t":"able","s":["G1410"]},{"t":"to refute or resist."}]},{"verse":16,"tokens":[{"t":"`And ye shall be"},{"t":"delivered","s":["G3860"]},{"t":"up also by"},{"t":"parents,","s":["G1118"]},{"t":"and"},{"t":"brothers,","s":["G80"]},{"t":"and kindred, and"},{"t":"friends,","s":["G5384"]},{"t":"and they shall put of you to death;"}]},{"verse":17,"tokens":[{"t":"and ye shall be"},{"t":"hated","s":["G3404"]},{"t":"by all because of my name --"}]},{"verse":18,"tokens":[{"t":"and a"},{"t":"hair","s":["G2359"]},{"t":"out of your"},{"t":"head","s":["G2776"]},{"t":"shall not perish;"}]},{"verse":19,"tokens":[{"t":"in your"},{"t":"patience","s":["G5281"]},{"t":"possess","s":["G2932"]},{"t":"ye your souls."}]},{"verse":20,"tokens":[{"t":"`And when ye may"},{"t":"see","s":["G1492"]},{"t":"Jerusalem","s":["G2419"]},{"t":"surrounded by encampments, then"},{"t":"know","s":["G1097"]},{"t":"that"},{"t":"come","s":["G2944"]},{"t":"nigh did her"},{"t":"desolation;","s":["G2050"]}]},{"verse":21,"tokens":[{"t":"then those in Judea, let them"},{"t":"flee","s":["G5343"]},{"t":"to the"},{"t":"mountains;","s":["G3735"]},{"t":"and those in her"},{"t":"midst,","s":["G3319"]},{"t":"let them"},{"t":"depart","s":["G1633"]},{"t":"out; and those in the"},{"t":"countries,","s":["G5561"]},{"t":"let them not"},{"t":"come","s":["G1525"]},{"t":"in to her;"}]},{"verse":22,"tokens":[{"t":"because these are"},{"t":"days","s":["G2250"]},{"t":"of"},{"t":"vengeance,","s":["G1557"]},{"t":"to fulfil all"},{"t":"things","s":["G3956"]},{"t":"that have been"},{"t":"written.","s":["G1125"]}]},{"verse":23,"tokens":[{"t":"`And wo to those with"},{"t":"child,","s":["G1064","G2192"]},{"t":"and to those giving"},{"t":"suck,","s":["G2337"]},{"t":"in those"},{"t":"days;","s":["G2250"]},{"t":"for there shall be"},{"t":"great","s":["G3173"]},{"t":"distress","s":["G318"]},{"t":"on the"},{"t":"land,","s":["G1093"]},{"t":"and"},{"t":"wrath","s":["G3709"]},{"t":"on this people;"}]},{"verse":24,"tokens":[{"t":"and they shall"},{"t":"fall","s":["G4098"]},{"t":"by the"},{"t":"mouth","s":["G4750"]},{"t":"of the"},{"t":"sword,","s":["G3162"]},{"t":"and shall be"},{"t":"led","s":["G163"]},{"t":"captive","s":["G163"]},{"t":"to all the"},{"t":"nations,","s":["G1484"]},{"t":"and"},{"t":"Jerusalem","s":["G2419"]},{"t":"shall be"},{"t":"trodden","s":["G3961"]},{"t":"down","s":["G3961"]},{"t":"by"},{"t":"nations,","s":["G1484"]},{"t":"till","s":["G891"]},{"t":"the"},{"t":"times","s":["G2540"]},{"t":"of"},{"t":"nations","s":["G1484"]},{"t":"be fulfilled."}]},{"verse":25,"tokens":[{"t":"`And there shall be"},{"t":"signs","s":["G4592"]},{"t":"in"},{"t":"sun,","s":["G2246"]},{"t":"and"},{"t":"moon,","s":["G4582"]},{"t":"and"},{"t":"stars,","s":["G798"]},{"t":"and on the"},{"t":"land","s":["G1093"]},{"t":"[is]"},{"t":"distress","s":["G4928"]},{"t":"of"},{"t":"nations","s":["G1484"]},{"t":"with"},{"t":"perplexity,","s":["G640"]},{"t":"sea","s":["G2281"]},{"t":"and billow roaring;"}]},{"verse":26,"tokens":[{"t":"men","s":["G444"]},{"t":"fainting at"},{"t":"heart","s":["G674"]},{"t":"from"},{"t":"fear,","s":["G5401"]},{"t":"and"},{"t":"expectation","s":["G4329"]},{"t":"of the"},{"t":"things","s":["G1904"]},{"t":"coming","s":["G1904"]},{"t":"on the"},{"t":"world,","s":["G3625"]},{"t":"for the"},{"t":"powers","s":["G1411"]},{"t":"of the"},{"t":"heavens","s":["G3772"]},{"t":"shall be shaken."}]},{"verse":27,"tokens":[{"t":"`And then they shall"},{"t":"see","s":["G3700"]},{"t":"the"},{"t":"Son","s":["G5207"]},{"t":"of"},{"t":"Man,","s":["G444"]},{"t":"coming","s":["G2064"]},{"t":"in a"},{"t":"cloud,","s":["G3507"]},{"t":"with"},{"t":"power","s":["G1411"]},{"t":"and"},{"t":"much","s":["G4183"]},{"t":"glory;"}]},{"verse":28,"tokens":[{"t":"and these"},{"t":"things","s":["G5130"]},{"t":"beginning","s":["G756"]},{"t":"to"},{"t":"happen","s":["G1096"]},{"t":"bend yourselves back, and"},{"t":"lift","s":["G1869"]},{"t":"up your"},{"t":"heads,","s":["G2776"]},{"t":"because your"},{"t":"redemption","s":["G629"]},{"t":"doth draw nigh.'"}]},{"verse":29,"tokens":[{"t":"And he"},{"t":"spake","s":["G2036"]},{"t":"a simile to them:"},{"t":"`See","s":["G1492"]},{"t":"the fig-tree, and all the trees,"}]},{"verse":30,"tokens":[{"t":"when they may now cast"},{"t":"forth,","s":["G4261"]},{"t":"having seen, of"},{"t":"yourselves","s":["G1438"]},{"t":"ye"},{"t":"know","s":["G1097"]},{"t":"that now is the"},{"t":"summer","s":["G2330"]},{"t":"nigh;"}]},{"verse":31,"tokens":[{"t":"so also ye, when ye may"},{"t":"see","s":["G1492"]},{"t":"these"},{"t":"things","s":["G5023"]},{"t":"happening,","s":["G1096"]},{"t":"ye"},{"t":"know","s":["G1097"]},{"t":"that near is the"},{"t":"reign","s":["G932"]},{"t":"of"},{"t":"God;","s":["G2316"]}]},{"verse":32,"tokens":[{"t":"verily","s":["G281"]},{"t":"I"},{"t":"say","s":["G3004"]},{"t":"to you -- This"},{"t":"generation","s":["G1074"]},{"t":"may not"},{"t":"pass","s":["G3928","G302"]},{"t":"away","s":["G3928","G302"]},{"t":"till","s":["G2193"]},{"t":"all may have come to pass;"}]},{"verse":33,"tokens":[{"t":"the"},{"t":"heaven","s":["G3772"]},{"t":"and the"},{"t":"earth","s":["G1093"]},{"t":"shall"},{"t":"pass","s":["G3928"]},{"t":"away,","s":["G3928"]},{"t":"but my"},{"t":"words","s":["G3056"]},{"t":"may not pass away."}]},{"verse":34,"tokens":[{"t":"`And"},{"t":"take","s":["G4337"]},{"t":"heed","s":["G4337"]},{"t":"to"},{"t":"yourselves,","s":["G1438"]},{"t":"lest","s":["G3379"]},{"t":"your"},{"t":"hearts","s":["G2588"]},{"t":"may be weighed down with"},{"t":"surfeiting,","s":["G2897"]},{"t":"and"},{"t":"drunkenness,","s":["G3178"]},{"t":"and anxieties of"},{"t":"life,","s":["G982"]},{"t":"and suddenly that"},{"t":"day","s":["G2250"]},{"t":"may"},{"t":"come","s":["G2186"]},{"t":"on you,"}]},{"verse":35,"tokens":[{"t":"for as a"},{"t":"snare","s":["G3803"]},{"t":"it shall"},{"t":"come","s":["G1904"]},{"t":"on all those dwelling on the"},{"t":"face","s":["G4383"]},{"t":"of all the land,"}]},{"verse":36,"tokens":[{"t":"watch","s":["G69"]},{"t":"ye, then, in every"},{"t":"season,","s":["G1722","G3956","G2540"]},{"t":"praying","s":["G1189"]},{"t":"that ye may be"},{"t":"accounted","s":["G2661"]},{"t":"worthy","s":["G2661"]},{"t":"to"},{"t":"escape","s":["G1628"]},{"t":"all these"},{"t":"things","s":["G5023"]},{"t":"that are about to"},{"t":"come","s":["G1096"]},{"t":"to"},{"t":"pass,","s":["G1096"]},{"t":"and to"},{"t":"stand","s":["G2476"]},{"t":"before","s":["G1715"]},{"t":"the"},{"t":"Son","s":["G5207"]},{"t":"of Man.'"}]},{"verse":37,"tokens":[{"t":"And he was during the"},{"t":"days","s":["G2250"]},{"t":"in the"},{"t":"temple","s":["G2411"]},{"t":"teaching,","s":["G1321"]},{"t":"and during the"},{"t":"nights,","s":["G3571"]},{"t":"going"},{"t":"forth,","s":["G1831"]},{"t":"he was lodging at the"},{"t":"mount","s":["G3735"]},{"t":"called","s":["G2564"]},{"t":"of Olives;"}]},{"verse":38,"tokens":[{"t":"and all the"},{"t":"people","s":["G2992"]},{"t":"were coming"},{"t":"early","s":["G3719"]},{"t":"unto him in the"},{"t":"temple","s":["G2411"]},{"t":"to"},{"t":"hear","s":["G191"]},{"t":"him."}]}]}